{"is_source_file": true, "format": "JavaScript (React JSX)", "description": "React component for the homepage of a web application, including SEO setup, animated sections, and imported subcomponents.", "external_files": ["../components/SEOHead", "../components/Hero", "../components/ServicesGrid", "../components/PortfolioGrid", "../components/TestimonialsSection", "../components/BlogList", "aos/dist/aos.css"], "external_methods": ["AOS.init"], "published": ["Home"], "classes": [], "methods": [{"name": "Home()", "description": "Main React functional component rendering the homepage sections with animations and SEO metadata.", "scope": "", "scopeKind": ""}], "calls": ["useEffect", "AOS.init"], "search-terms": ["React", "Homepage", "SEOHead", "AOS", "Hero", "ServicesGrid", "PortfolioGrid", "TestimonialsSection", "BlogList"], "state": 2, "file_id": 25, "knowledge_revision": 55, "git_revision": "", "ctags": [{"_type": "tag", "name": "Home", "path": "/home/kavia/workspace/code-generation/technova-solutions-platform-105006-104789/technova_frontend/src/pages/Home.js", "pattern": "/^export default function Home() {$/", "language": "JavaScript", "kind": "function", "signature": "()"}], "hash": "1cd83e4ba30526ead2902ec01a158fff", "format-version": 4, "code-base-name": "technova_frontend", "filename": "technova_frontend/src/pages/Home.js", "revision_history": [{"55": ""}]}